django_restful/__init__.py
django_restful/base.py
django_restful/decorators.py
django_restful/error.py
django_restful/response.py
django_restful/utils/__init__.py
django_restful/utils/parse.py
django_restful/utils/url.py
django_restful-0.0.6.dist-info/DESCRIPTION.rst
django_restful-0.0.6.dist-info/METADATA
django_restful-0.0.6.dist-info/RECORD
django_restful-0.0.6.dist-info/WHEEL
django_restful-0.0.6.dist-info/metadata.json
django_restful-0.0.6.dist-info/top_level.txt
