Metadata-Version: 2.0
Name: django-restful
Version: 0.0.6
Summary: django_restful
Home-page: http://www.hshl.ltd
Author: bigtiger
Author-email: chinafengheping@gmail.com
License: UNKNOWN
Platform: UNKNOWN
Requires-Dist: djangorestframework (>=3.3.1)
Requires-Dist: six
